LICENSE
drf_operation_log/__init__.py
drf_operation_log/admin.py
drf_operation_log/apps.py
drf_operation_log/encoders.py
drf_operation_log/migrations/0001_initial.py
drf_operation_log/migrations/0002_auto_20220428_1916.py
drf_operation_log/migrations/0003_operationlogentry_extra.py
drf_operation_log/migrations/0004_operationlogentry_object_repr.py
drf_operation_log/migrations/__init__.py
drf_operation_log/mixins.py
drf_operation_log/models.py
drf_operation_log/serializers.py
drf_operation_log/signals.py
drf_operation_log/urls.py
drf_operation_log/utils.py
drf_operation_log/views.py
drf_operation_log-1.0.1.dist-info/LICENSE
drf_operation_log-1.0.1.dist-info/WHEEL
drf_operation_log-1.0.1.dist-info/METADATA
drf_operation_log-1.0.1.dist-info/RECORD
